typepeek/__init__.py
typepeek/infer.py
typepeek/logger_config.py
typepeek-0.3.0.dist-info/licenses/LICENSE
typepeek-0.3.0.dist-info/METADATA
typepeek-0.3.0.dist-info/WHEEL
typepeek-0.3.0.dist-info/top_level.txt
typepeek-0.3.0.dist-info/RECORD
