Metadata-Version: 2.4
Name: typepeek
Version: 0.3.0
Summary: Infer type hints from runtime Python data
Home-page: https://github.com/Mikyx-1/typepeek
Author: Le Hoang Viet
Author-email: Le Hoang Viet <lehoangviet2k@gmail.com>
License: MIT
Project-URL: Homepage, https://github.com/Mikyx-1/typepeek
Project-URL: Repository, https://github.com/Mikyx-1/typepeek
Platform: any
Requires-Python: >=3.7
License-File: LICENSE
Dynamic: author
Dynamic: home-page
Dynamic: license-file
Dynamic: platform
Dynamic: requires-python
